vowels_counter/__init__.py
vowels_counter/vowels_counter.py
vowels_counter1.0-0.1.1.dist-info/METADATA
vowels_counter1.0-0.1.1.dist-info/WHEEL
vowels_counter1.0-0.1.1.dist-info/top_level.txt
vowels_counter1.0-0.1.1.dist-info/RECORD
